imufusion.cpython-38-x86_64-linux-gnu.so
test_imufusion-0.0.76.dist-info/top_level.txt
test_imufusion-0.0.76.dist-info/LICENSE.md
test_imufusion-0.0.76.dist-info/WHEEL
test_imufusion-0.0.76.dist-info/METADATA
test_imufusion-0.0.76.dist-info/RECORD
