Metadata-Version: 2.1
Name: test-imufusion
Version: 0.0.76
Summary: Fusion Python package
Home-page: https://github.com/xioTechnologies/Fusion
Author: x-io Technologies Limited
Author-email: info@x-io.co.uk
License: MIT
Platform: UNKNOWN
Classifier: Programming Language :: Python :: 3.8
Classifier: Programming Language :: Python :: 3.9
Classifier: Programming Language :: Python :: 3.10
